vacation_tracker.py
vacation_tracker-0.1.4.dist-info/licenses/LICENSE
vacation_tracker-0.1.4.dist-info/METADATA
vacation_tracker-0.1.4.dist-info/WHEEL
vacation_tracker-0.1.4.dist-info/entry_points.txt
vacation_tracker-0.1.4.dist-info/top_level.txt
vacation_tracker-0.1.4.dist-info/RECORD
