Metadata-Version: 2.4
Name: vacation-tracker
Version: 0.1.4
Summary: Track number of remaining vacation days.
Author-email: Tim Hörmann <pypi@audivir.de>
License-Expression: MIT
Project-URL: Homepage, https://github.com/audivir/vacation-tracker
Project-URL: Repository, https://github.com/audivir/vacation-tracker
Classifier: Programming Language :: Python :: 3
Requires-Python: >=3.9
License-File: LICENSE
Requires-Dist: doctyper
Requires-Dist: holidays
Requires-Dist: msgspec[toml]
Requires-Dist: polars
Provides-Extra: dev
Requires-Dist: ruff; extra == "dev"
Requires-Dist: mypy; extra == "dev"
Requires-Dist: pytest; extra == "dev"
Requires-Dist: coverage[toml]; extra == "dev"
Requires-Dist: vulture; extra == "dev"
Dynamic: license-file
